demexpy/__init__.py
demexpy/encryption.py
demexpy/nodes.py
demexpy/scripts.py
demexpy/utils.py
demexpy-0.8.7.dist-info/licenses/LICENSE
demexpy-0.8.7.dist-info/METADATA
demexpy-0.8.7.dist-info/WHEEL
demexpy-0.8.7.dist-info/entry_points.txt
demexpy-0.8.7.dist-info/top_level.txt
demexpy-0.8.7.dist-info/RECORD
