Metadata-Version: 2.4
Name: demexpy
Version: 0.8.7
Summary: Python implementation of the DeMeX protocol
Author-email: Abdullah Alam <abdullah@sentient-pixels.com>
Maintainer-email: Abdullah Alam <abdullah@sentient-pixels.com>
License-Expression: MIT
Project-URL: Homepage, https://github.com/sentientpixels/demexpy
Project-URL: Documentation, https://github.com/sentientpixels/demexpy/blob/main/docs/index.md
Project-URL: Repository, https://github.com/sentientpixels/demexpy
Keywords: demex,message broker,decentralised,decentralized,send messages
Requires-Python: >=3.8
License-File: LICENSE
Requires-Dist: requests
Requires-Dist: cryptography
Dynamic: license-file
